gdmty_drf_firebase_auth/__init__.py
gdmty_drf_firebase_auth/admin.py
gdmty_drf_firebase_auth/apps.py
gdmty_drf_firebase_auth/authentication.py
gdmty_drf_firebase_auth/models.py
gdmty_drf_firebase_auth/settings.py
gdmty_drf_firebase_auth/tests.py
gdmty_drf_firebase_auth/utils.py
gdmty_drf_firebase_auth/views.py
gdmty_drf_firebase_auth/migrations/0001_initial.py
gdmty_drf_firebase_auth/migrations/0002_initial.py
gdmty_drf_firebase_auth/migrations/__init__.py
gdmty_drf_firebase_auth-24.5.3.dist-info/LICENSE
gdmty_drf_firebase_auth-24.5.3.dist-info/METADATA
gdmty_drf_firebase_auth-24.5.3.dist-info/WHEEL
gdmty_drf_firebase_auth-24.5.3.dist-info/top_level.txt
gdmty_drf_firebase_auth-24.5.3.dist-info/RECORD
