Metadata-Version: 2.1
Name: gdmty-drf-firebase-auth
Version: 24.5.3
Summary: Custom Django Rest Framework authentication backend than can be used with many firebase projects at same time, and storing as local users.
Author-email: Gobierno de Monterrey <cesar.benjamin@monterrey.gob.mx>
License: Apache License
Project-URL: Homepage, https://github.com/SIGAMty/gdmty-drf-firebase-auth
Project-URL: Bug Tracker, https://github.com/SIGAMty/gdmty-drf-firebase-auth/issues
Keywords: django,firebase,jwt,authentication
Classifier: License :: OSI Approved :: Apache Software License
Classifier: Programming Language :: Python
Classifier: Programming Language :: Python :: 3
Classifier: Programming Language :: Python :: 3.10
Classifier: Programming Language :: Python :: 3.11
Classifier: Framework :: Django
Requires-Python: >=3.10
License-File: LICENSE
Requires-Dist: django <6.0,>=4.1.3
Requires-Dist: firebase-admin
Requires-Dist: djangorestframework
Requires-Dist: tomli ; python_version < "3.11"
Provides-Extra: dev
Requires-Dist: black ; extra == 'dev'
Requires-Dist: bumpver ; extra == 'dev'
Requires-Dist: isort ; extra == 'dev'
Requires-Dist: pip-tools ; extra == 'dev'
Requires-Dist: pytest ; extra == 'dev'
